m18writer/__init__.py
m18writer/writer.py
m1_8_writer-0.9.2.dist-info/LICENSE
m1_8_writer-0.9.2.dist-info/METADATA
m1_8_writer-0.9.2.dist-info/WHEEL
m1_8_writer-0.9.2.dist-info/entry_points.txt
m1_8_writer-0.9.2.dist-info/top_level.txt
m1_8_writer-0.9.2.dist-info/RECORD
