Metadata-Version: 2.1
Name: m1-8-writer
Version: 0.9.2
Summary: LED name badge writer.
Home-page: https://github.com/amane-katagiri/m1-8-writer
Author: Amane Katagiri
Author-email: amane@ama.ne.jp
License: MIT
Keywords: led,badge,usb,serial,m1-8
Platform: UNKNOWN
Classifier: Development Status :: 3 - Alpha
Classifier: License :: OSI Approved :: MIT License
Classifier: Programming Language :: Python :: 3.7
Requires-Dist: pyserial
Requires-Dist: Pillow
Requires-Dist: numpy
